rezen/__init__.py
rezen/agents.py
rezen/api_keys.py
rezen/auth.py
rezen/base_client.py
rezen/checklist.py
rezen/client.py
rezen/directory.py
rezen/documents.py
rezen/dropbox.py
rezen/enums.py
rezen/exceptions.py
rezen/mfa.py
rezen/models.py
rezen/py.typed
rezen/rev_share.py
rezen/teams.py
rezen/transaction_builder.py
rezen/transactions.py
rezen/users.py
rezen-2.2.15.dist-info/licenses/LICENSE
rezen-2.2.15.dist-info/METADATA
rezen-2.2.15.dist-info/WHEEL
rezen-2.2.15.dist-info/top_level.txt
rezen-2.2.15.dist-info/RECORD
