Metadata-Version: 2.4
Name: rezen
Version: 2.2.15
Summary: Python wrapper for The Real Brokerage ReZEN API - Transaction Builder, Transactions, Teams, Agents, and Directory management
Author-email: The Perry Group <dev@theperrygroup.com>
Maintainer-email: The Perry Group <dev@theperrygroup.com>
License: MIT License
Project-URL: Homepage, https://github.com/theperrygroup/rezen
Project-URL: Documentation, https://theperrygroup.github.io/rezen/
Project-URL: Repository, https://github.com/theperrygroup/rezen
Project-URL: Bug Tracker, https://github.com/theperrygroup/rezen/issues
Project-URL: Changelog, https://github.com/theperrygroup/rezen/releases
Keywords: real-estate,api,transactions,realty,rezen,the-real-brokerage,real-estate-api,transaction-management
Classifier: Development Status :: 5 - Production/Stable
Classifier: Intended Audience :: Developers
Classifier: Intended Audience :: Financial and Insurance Industry
Classifier: Operating System :: OS Independent
Classifier: Programming Language :: Python :: 3
Classifier: Programming Language :: Python :: 3.8
Classifier: Programming Language :: Python :: 3.9
Classifier: Programming Language :: Python :: 3.10
Classifier: Programming Language :: Python :: 3.11
Classifier: Programming Language :: Python :: 3.12
Classifier: Topic :: Office/Business :: Financial
Classifier: Topic :: Software Development :: Libraries :: Python Modules
Classifier: Topic :: Internet :: WWW/HTTP :: Dynamic Content
Classifier: Typing :: Typed
Requires-Python: >=3.8
License-File: LICENSE
Requires-Dist: requests>=2.31.0
Requires-Dist: pydantic>=2.5.0
Requires-Dist: typing-extensions>=4.8.0
Provides-Extra: dotenv
Requires-Dist: python-dotenv>=1.0.0; extra == "dotenv"
Provides-Extra: dev
Requires-Dist: python-dotenv>=1.0.0; extra == "dev"
Requires-Dist: pytest>=7.4.0; extra == "dev"
Requires-Dist: pytest-cov>=4.1.0; extra == "dev"
Requires-Dist: pytest-mock>=3.12.0; extra == "dev"
Requires-Dist: responses>=0.24.0; extra == "dev"
Requires-Dist: black>=23.9.0; extra == "dev"
Requires-Dist: flake8>=6.1.0; extra == "dev"
Requires-Dist: mypy>=1.6.0; extra == "dev"
Requires-Dist: isort>=5.12.0; extra == "dev"
Requires-Dist: pylint>=3.0.0; extra == "dev"
Requires-Dist: types-requests>=2.31.0; extra == "dev"
Dynamic: license-file
